django_sql_comment/__init__.py
django_sql_comment/management/__init__.py
django_sql_comment/management/commands/__init__.py
django_sql_comment/management/commands/sqlcomment.py
django_sql_comment-1.0.0.dist-info/METADATA
django_sql_comment-1.0.0.dist-info/WHEEL
django_sql_comment-1.0.0.dist-info/top_level.txt
django_sql_comment-1.0.0.dist-info/RECORD
