Metadata-Version: 2.1
Name: django-sql-comment
Version: 1.0.0
Summary: Django management command to generate SQL for applying your models' verbose name and help_text as PostgreSQL COMMENTs
Home-page: https://github.com/tuffnatty/django-sql-comment
Author: Phil Krylov
Author-email: phil.krylov@gmail.com
License: MIT
Keywords: django-sql-comment
Classifier: Development Status :: 5 - Production/Stable
Classifier: Framework :: Django :: 1.11
Classifier: Framework :: Django :: 2
Classifier: Framework :: Django :: 3
Classifier: Framework :: Django :: 4.0
Classifier: Framework :: Django :: 4.1
Classifier: Framework :: Django :: 4.2
Classifier: Intended Audience :: Developers
Classifier: License :: OSI Approved :: BSD License
Classifier: Programming Language :: Python :: 2
Classifier: Programming Language :: Python :: 2.7
Classifier: Programming Language :: Python :: 3
Classifier: Programming Language :: Python :: 3.4
Classifier: Programming Language :: Python :: 3.5
Classifier: Programming Language :: Python :: 3.6
Classifier: Programming Language :: Python :: 3.7
Classifier: Programming Language :: Python :: 3.8
Classifier: Programming Language :: Python :: 3.9
Classifier: Programming Language :: Python :: 3.10
Classifier: Programming Language :: Python :: 3.11
Classifier: Topic :: Database
Classifier: Topic :: Software Development :: Documentation
